{
  "docVersion": "1.0.0",
  "resource": {
    "name": "SendWhatsApp",
    "kind": "process",
    "type": "process",
    "apiVersion": "orchestrator.uipath.com/v1",
    "projectKey": "c6d107d1-1ac6-442d-8ef1-4022ccf572ab",
    "isOverridable": true,
    "dependencies": [
      {
        "name": "SendWhatsApp",
        "kind": "package"
      }
    ],
    "runtimeDependencies": [],
    "files": [],
    "folders": [
      {
        "fullyQualifiedName": "solution_folder"
      }
    ],
    "spec": {
      "entryPointUniqueId": null,
      "inputArgumentsSchema": null,
      "outputArgumentsSchema": null,
      "inputArgumentsSchemaV2": null,
      "outputArgumentsSchemaV2": null,
      "type": "Process",
      "name": "SendWhatsApp",
      "description": null,
      "package": {
        "key": "54172b8a-e4b3-4cb8-a77f-30fc14dcc36c"
      },
      "packageName": "Solution.4.process.SendWhatsApp",
      "packageVersion": null,
      "entryPointName": null,
      "inputArguments": null,
      "jobPriority": "Medium",
      "hiddenForAttendedUser": false,
      "alwaysRunning": false,
      "autoStartProcess": false,
      "jobRecording": "Disabled",
      "targetFrameworkValue": "Portable",
      "duration": 40,
      "frequency": 500,
      "quality": 100,
      "remoteControlAccess": "None",
      "retentionAction": "Delete",
      "retentionPeriod": 30,
      "retentionBucketRef": null,
      "staleRetentionAction": "Delete",
      "staleRetentionPeriod": 180,
      "staleRetentionBucketRef": null,
      "entryPoints": null,
      "connections": null,
      "tags": []
    },
    "locks": [],
    "key": "704e250e-afb7-4a15-867b-916a82f07edf"
  }
}